ArrImputer/ArrImpute.py
ArrImputer/__init__.py
ArrImputer/__main__.py
ArrImputer/utils.py
LICENSE
arrimputer-1.3.0.dist-info/LICENSE
arrimputer-1.3.0.dist-info/METADATA
arrimputer-1.3.0.dist-info/WHEEL
arrimputer-1.3.0.dist-info/RECORD
