Metadata-Version: 2.1
Name: arrimputer
Version: 1.3.0
Summary: A machine learning package for testing integer imputation into arrays and checking out changes in the cost. Looking for ways to extend this to dataframes as it has great potential
Home-page: https://github.com/alphaprime7/Imputer
License: MIT
Author: Tingwei Adeck
Author-email: awesome.tingwei@outlook.com
Requires-Python: >=3.12,<4.0
Classifier: Environment :: Console
Classifier: Framework :: Flake8
Classifier: License :: OSI Approved :: MIT License
Classifier: Operating System :: OS Independent
Classifier: Programming Language :: Python :: 3
Classifier: Programming Language :: Python :: 3.12
Classifier: Topic :: Software Development :: Documentation
Classifier: Topic :: Software Development :: Libraries :: Python Modules
Classifier: Topic :: Software Development :: Quality Assurance
Requires-Dist: numpy (>=1.26.4,<2.0.0)
Project-URL: Repository, https://github.com/alphaprime7/Imputer
